quicktimer/__init__.py
quicktimer/quicktimer.py
quicktimer-0.2.0.dist-info/LICENSE
quicktimer-0.2.0.dist-info/METADATA
quicktimer-0.2.0.dist-info/WHEEL
quicktimer-0.2.0.dist-info/top_level.txt
quicktimer-0.2.0.dist-info/RECORD
