Metadata-Version: 2.1
Name: quicktimer
Version: 0.2.0
Summary: Tracking code performance easily.
Home-page: https://github.com/CribberSix/QuickTimer
Author: CribberSix
Author-email: cribbersix@gmail.com
License: MIT
Keywords: tracking,time
Platform: UNKNOWN
Classifier: Development Status :: 5 - Production/Stable
Classifier: License :: OSI Approved :: MIT License
Classifier: Programming Language :: Python :: 3
Classifier: Programming Language :: Python :: 3.6
Classifier: Topic :: Software Development :: Libraries
Classifier: Topic :: Software Development :: Libraries :: Python Modules
Classifier: Intended Audience :: Developers
Classifier: Natural Language :: English
Classifier: Topic :: Software Development
Requires-Python: >=3.6
